[
    {
        "img": "https://www.sriveluenterprises.com/machines/Mi08j-11.jpeg",
        "title": "TSUGAMI",
        "type": "Mi08j-11",
        "make": "HAAS",
        "quantity": "6",
        "xmm": "762",
        "xinch": "30",
        "ymm": "406",
        "yinch": "16",
        "zmm": "508",
        "zinch": "20"
      },
      {
        "img": "https://www.sriveluenterprises.com/machines/Smartturn.jpeg",
        "title": "LMW",
        "type": "SMART TURN",
        "make": "HAAS",
        "quantity": "2",
        "xmm": "762",
        "xinch": "30",
        "ymm": "406",
        "yinch": "16",
        "zmm": "508",
        "zinch": "20"
      },
      {
        "img": "https://www.sriveluenterprises.com/machines/LX20TL3.jpeg",
        "title": "LMW",
        "type": "LX20T L3",
        "make": "HAAS",
        "quantity": "2",
        "xmm": "762",
        "xinch": "30",
        "ymm": "406",
        "yinch": "16",
        "zmm": "508",
        "zinch": "20"
      },
      {
        "img": "https://www.sriveluenterprises.com/machines/hwacheon.jpeg",
        "title": "hwacheon machine tool co ltd",
        "type": "Cutex - 160a i",
        "make": "HAAS",
        "quantity": "1",
        "xmm": "762",
        "xinch": "30",
        "ymm": "406",
        "yinch": "16",
        "zmm": "508",
        "zinch": "20"
      },
      {
        "img": "https://www.sriveluenterprises.com/machines/LMWLL20T.jpg",
        "title": "LMW LL20T L5 CNC Lathes",
        "type": "LL20TL5",
        "make": "HAAS",
        "quantity": "1",
        "xmm": "762",
        "xinch": "30",
        "ymm": "406",
        "yinch": "16",
        "zmm": "508",
        "zinch": "20"
      },
      {
        "img": "https://www.sriveluenterprises.com/machines/Arrow2.jpeg",
        "title": "CINCINNATI",
        "type": "VMC ARROW 2",
        "make": "HAAS",
        "quantity": "1",
        "xmm": "762",
        "xinch": "30",
        "ymm": "406",
        "yinch": "16",
        "zmm": "508",
        "zinch": "20"
      },
      {
        "img": "https://www.sriveluenterprises.com/machines/SV 150.jpeg",
        "title": "HARDINGE",
        "type": "SV 150",
        "make": "HAAS",
        "quantity": "1",
        "xmm": "762",
        "xinch": "30",
        "ymm": "406",
        "yinch": "16",
        "zmm": "508",
        "zinch": "20"
      }
]